Workbook

Sheet Dashboard
A1: ☕💣 Bellacosa Mainframe - Simulador de Investimentos
A3: Valor Inicial | B3: 1000
A4: Aporte Mensal | B4: 500
A5: Taxa Mensal (%) | B5: 0.8
A6: Prazo (Anos) | B6: 10
A7: Dividend Yield (%) | B7: 0.8
A10: Meses | B10: =B6*12
A11: Total Investido | B11: =B4*B10+B3
A12: Patrimônio Futuro | B12: =FV(B5/100,B10,-B4,-B3,0)
A13: Dividendos Mensais | B13: =B12*(B7/100)

Sheet Evolucao
A1: Ano | B1: Patrimonio
A2: 1 | B2: =FV(Dashboard!B5/100,1*12,-Dashboard!B4,-Dashboard!B3,0)
A3: 2 | B3: =FV(Dashboard!B5/100,2*12,-Dashboard!B4,-Dashboard!B3,0)
A4: 3 | B4: =FV(Dashboard!B5/100,3*12,-Dashboard!B4,-Dashboard!B3,0)
A5: 4 | B5: =FV(Dashboard!B5/100,4*12,-Dashboard!B4,-Dashboard!B3,0)
A6: 5 | B6: =FV(Dashboard!B5/100,5*12,-Dashboard!B4,-Dashboard!B3,0)
A7: 6 | B7: =FV(Dashboard!B5/100,6*12,-Dashboard!B4,-Dashboard!B3,0)
A8: 7 | B8: =FV(Dashboard!B5/100,7*12,-Dashboard!B4,-Dashboard!B3,0)
A9: 8 | B9: =FV(Dashboard!B5/100,8*12,-Dashboard!B4,-Dashboard!B3,0)
A10: 9 | B10: =FV(Dashboard!B5/100,9*12,-Dashboard!B4,-Dashboard!B3,0)
A11: 10 | B11: =FV(Dashboard!B5/100,10*12,-Dashboard!B4,-Dashboard!B3,0)
A12: 11 | B12: =FV(Dashboard!B5/100,11*12,-Dashboard!B4,-Dashboard!B3,0)
A13: 12 | B13: =FV(Dashboard!B5/100,12*12,-Dashboard!B4,-Dashboard!B3,0)
A14: 13 | B14: =FV(Dashboard!B5/100,13*12,-Dashboard!B4,-Dashboard!B3,0)
A15: 14 | B15: =FV(Dashboard!B5/100,14*12,-Dashboard!B4,-Dashboard!B3,0)
A16: 15 | B16: =FV(Dashboard!B5/100,15*12,-Dashboard!B4,-Dashboard!B3,0)
A17: 16 | B17: =FV(Dashboard!B5/100,16*12,-Dashboard!B4,-Dashboard!B3,0)
A18: 17 | B18: =FV(Dashboard!B5/100,17*12,-Dashboard!B4,-Dashboard!B3,0)
A19: 18 | B19: =FV(Dashboard!B5/100,18*12,-Dashboard!B4,-Dashboard!B3,0)
A20: 19 | B20: =FV(Dashboard!B5/100,19*12,-Dashboard!B4,-Dashboard!B3,0)
A21: 20 | B21: =FV(Dashboard!B5/100,20*12,-Dashboard!B4,-Dashboard!B3,0)
A22: 21 | B22: =FV(Dashboard!B5/100,21*12,-Dashboard!B4,-Dashboard!B3,0)
A23: 22 | B23: =FV(Dashboard!B5/100,22*12,-Dashboard!B4,-Dashboard!B3,0)
A24: 23 | B24: =FV(Dashboard!B5/100,23*12,-Dashboard!B4,-Dashboard!B3,0)
A25: 24 | B25: =FV(Dashboard!B5/100,24*12,-Dashboard!B4,-Dashboard!B3,0)
A26: 25 | B26: =FV(Dashboard!B5/100,25*12,-Dashboard!B4,-Dashboard!B3,0)
A27: 26 | B27: =FV(Dashboard!B5/100,26*12,-Dashboard!B4,-Dashboard!B3,0)
A28: 27 | B28: =FV(Dashboard!B5/100,27*12,-Dashboard!B4,-Dashboard!B3,0)
A29: 28 | B29: =FV(Dashboard!B5/100,28*12,-Dashboard!B4,-Dashboard!B3,0)
A30: 29 | B30: =FV(Dashboard!B5/100,29*12,-Dashboard!B4,-Dashboard!B3,0)
A31: 30 | B31: =FV(Dashboard!B5/100,30*12,-Dashboard!B4,-Dashboard!B3,0)

Sheet Cenarios
A1: Cenário | B1: Taxa | C1: Patrimônio
A2: Conservador | B2: 0.6 | C2: =FV(B2/100,120,-500,-1000,0)
A3: Moderado | B3: 0.8 | C3: =FV(B3/100,120,-500,-1000,0)
A4: Agressivo | B4: 1 | C4: =FV(B4/100,120,-500,-1000,0)

Sheet Indicadores
A1: Indicador | B1: Fórmula
A2: ROI | B2: (Patrimônio-Total Investido)/Total Investido
A3: CAGR | B3: (VF/VI)^(1/anos)-1
A4: Dividend Yield | B4: Dividendos/Cota
A5: Renda Passiva | B5: Patrimônio x DY
